odoo/addons/portal_odoo_debranding/README.rst
odoo/addons/portal_odoo_debranding/__init__.py
odoo/addons/portal_odoo_debranding/__manifest__.py
odoo/addons/portal_odoo_debranding/i18n/portal_odoo_debranding.pot
odoo/addons/portal_odoo_debranding/readme/CONTRIBUTORS.rst
odoo/addons/portal_odoo_debranding/readme/DESCRIPTION.rst
odoo/addons/portal_odoo_debranding/static/description/icon.png
odoo/addons/portal_odoo_debranding/static/description/index.html
odoo/addons/portal_odoo_debranding/views/portal_templates.xml
odoo14_addon_portal_odoo_debranding-14.0.1.0.1.dist-info/METADATA
odoo14_addon_portal_odoo_debranding-14.0.1.0.1.dist-info/WHEEL
odoo14_addon_portal_odoo_debranding-14.0.1.0.1.dist-info/top_level.txt
odoo14_addon_portal_odoo_debranding-14.0.1.0.1.dist-info/RECORD
