Metadata-Version: 2.1
Name: odoo14-addon-portal-odoo-debranding
Version: 14.0.1.0.1
Summary: Remove Odoo Branding from Portal
Home-page: https://github.com/OCA/server-brand
Author: TAKOBI, Odoo Community Association (OCA), Ilyas, Ooops404,
Author-email: support@odoo-community.org
License: LGPL-3
Platform: UNKNOWN
Classifier: Programming Language :: Python
Classifier: Framework :: Odoo
Classifier: Framework :: Odoo :: 14.0
Classifier: License :: OSI Approved :: GNU Lesser General Public License v3 (LGPLv3)
Classifier: Development Status :: 4 - Beta
Requires-Python: >=3.6
Requires-Dist: odoo (<14.1dev,>=14.0a)
